hockey.v
module hockey(

    input clk,
    input rst,

    input BTNA,
    input BTNB,

    input [1:0] DIRA,
    input [1:0] DIRB,

    input [2:0] YA,
    input [2:0] YB,

    output reg LEDA,
    output reg LEDB,
    output reg [4:0] LEDX,

    output reg [6:0] SSD7,
    output reg [6:0] SSD6,
    output reg [6:0] SSD5,
    output reg [6:0] SSD4,
    output reg [6:0] SSD3,
    output reg [6:0] SSD2,
    output reg [6:0] SSD1,
    output reg [6:0] SSD0 ,

    output reg [2:0] XCOORD,
    output reg [2:0] YCOORD

  );



  reg turn;
  reg [3:0] state;

  reg starttimer;
  reg [8:0] timer;
  reg [1:0] dirY;

  reg [1:0] scoreA;
  reg [1:0] scoreB;

  parameter IDLE = 4'b0000;
  parameter DSP = 4'b0001;
  parameter HITB = 4'b0010;
  parameter HITA = 4'b0011;
  parameter SENDB = 4'b0100;
  parameter SENDA = 4'b0101;
  parameter RESPA =4'b0110;
  parameter RESPB =4'b0111;
  parameter GOALA =4'b1000;
  parameter GOALB =4'b1001;
  parameter FINISH = 4'b1010;
  parameter BLINK = 4'b1011;

  parameter ZERO = 7'b0000001;
  parameter ONE = 7'b1001111;
  parameter TWO = 7'b0010010;
  parameter THREE = 7'b0000110;
  parameter FOUR = 7'b1001100;
  parameter NONE = 7'b1111111;


  reg [1:0] buttons;

  // you may use additional always blocks or drive SSDs and LEDs in one always block
  // for state machine and memory elements
  always @(posedge clk or posedge rst)
  begin
    if(rst)
    begin
      state <= IDLE;
      XCOORD = 0;
      YCOORD = 0;
      timer <= 0;
      scoreA <= 0;
      scoreB <= 0;
    end
    else
    case(state)
      IDLE:
      begin
        buttons = {BTNA,BTNB};
        case(buttons)
          2'b01:
          begin
            turn <= 1'b1;
            state <= DSP;
          end
          2'b10:
          begin
            turn <= 1'b0;
            state <= DSP;
          end
          default:
          begin
            turn <= 1;
            state <= IDLE;
          end
        endcase
      end

      DSP:
      begin
        if(timer < 100)
        begin
          timer <= timer+1;
          state <= DSP;
        end
        else
        begin
          $display("hdfkasfgka");
          if(turn)
            state <= HITB;
          else
            state <= HITA;
          timer <= 0;
        end
      end

      HITB:
      begin
        if(BTNB && YB < 5)
        begin
          XCOORD <= 4;
          YCOORD <= YB;
          dirY <= DIRB;
          state <= SENDA;
        end
        else
          state <= HITB;
      end

      HITA:
      begin
        if(BTNA && YA < 5)
        begin
          XCOORD <= 0;
          YCOORD <= YA;
          dirY <= DIRA;
          state <= SENDB;
        end
        else
          state <= HITA;
      end

      SENDA:
      begin
        if(timer < 100)
        begin
          timer <= timer+1;
          state <= SENDA;
        end
        else
        begin
          timer <= 0;
          if(dirY == 2'b10)
          begin

            if(YCOORD == 3'b000)
            begin
              dirY <= 2'b01;
              YCOORD <= YCOORD + 1;
            end

            else
              YCOORD <= YCOORD - 1;
          end

          else if(dirY == 2'b01)
          begin

            if(YCOORD == 3'b100)
            begin
              dirY <= 2'b10;
              YCOORD <= YCOORD - 1;
            end

            else
              YCOORD <= YCOORD + 1;
          end

          if(XCOORD > 1)
          begin
            XCOORD <= XCOORD-1;
            state <= SENDA;
          end
          else
          begin
            XCOORD <= 0;
            state <= RESPA;
          end
        end
      end

      SENDB:
      begin
        if(timer < 100)
        begin
          timer <= timer+1;
          state <= SENDB;
        end
        else
        begin
          timer <= 0;
          if(dirY == 2'b10)
          begin

            if(YCOORD == 3'b000)
            begin
              dirY <= 2'b01;
              YCOORD <= YCOORD + 1;
            end

            else
              YCOORD <= YCOORD - 1;
          end

          else if(dirY == 2'b01)
          begin

            if(YCOORD == 3'b100)
            begin
              dirY <= 2'b10;
              YCOORD <= YCOORD - 1;
            end

            else
              YCOORD <= YCOORD + 1;
          end


          if(XCOORD < 3 )
          begin
            XCOORD <= XCOORD + 1;
            state <= SENDB;
          end
          else
          begin
            XCOORD <= 4;
            state <= RESPB;
          end
        end
      end

      RESPA:
      begin
        if(timer < 100)
        begin
          if(BTNA && YCOORD == YA)
          begin
            XCOORD <= 1;
            timer <= 0;
            if(DIRB == 2'b00)
            begin
              dirY <= DIRB;
            end
            else if(DIRB == 2'b01)
            begin
              if(YCOORD == 4)
              begin
                dirY <= 2'b10;
                YCOORD <= YCOORD -1;
              end
              else
              begin
                dirY <= DIRA;
                YCOORD <= YCOORD + 1;
              end
            end
            else if(DIRB == 2'b10)
            begin
              if(YCOORD == 0)
              begin
                dirY <= 2'b01;
                YCOORD <= YCOORD + 1;
              end
              else
              begin
                dirY <= DIRA;
                YCOORD <= YCOORD - 1;
              end
            end
            else
            begin
              state <= IDLE;
            end
            state <= SENDB;
          end
          else
            timer <= timer + 1;
        end
        else
        begin
          timer <= 0;
          scoreB <= scoreB + 1;
          state <= GOALB;
        end
      end

      RESPB:
      begin
        if(timer < 100)
        begin
          if(BTNB && YCOORD == YB)
          begin
            XCOORD <= 3;
            timer <= 0;
            if(DIRA == 2'b00)
            begin
              dirY <= DIRA;
            end
            else if(DIRA == 2'b01)
            begin
              if(YCOORD == 4)
              begin
                dirY <= 2'b10;
                YCOORD <= YCOORD -1;
              end
              else
              begin
                dirY <= DIRB;
                YCOORD <= YCOORD + 1;
              end
            end
            else if(DIRA == 2'b10)
            begin
              if(YCOORD == 0)
              begin
                dirY <= 2'b01;
                YCOORD <= YCOORD + 1;
              end
              else
              begin
                dirY <= DIRB;
                YCOORD <= YCOORD - 1;
              end
            end
            else
              state <= IDLE;
            state <= SENDA;
          end
          else
            timer <= timer + 1;
        end
        else
        begin
          timer <= 0;
          scoreA <= scoreA + 1;
          state <= GOALA;
        end
      end

      GOALB:
      begin
        if(timer < 100)
        begin
          timer <= timer + 1;
          state <= GOALB;
        end
        else
        begin
          timer <= 0;
          if(scoreB == 3)
          begin
            turn <= 1;
            state <= FINISH;
          end
          else
            state <= HITA;
        end
      end

      GOALA:
      begin
        if(timer < 100)
        begin
          timer <= timer + 1;
          state <= GOALA;
        end
        else
        begin
          timer <= 0;
          if(scoreA == 3)
          begin
            turn <= 0;
            state <= FINISH;
          end
          else
            state <= HITB;
        end
      end

      FINISH:
        if(timer < 25)
        begin
          timer <= timer +1;
          state <= FINISH;
        end
        else
        begin
          timer <= 0;
          state <= BLINK;
        end
      BLINK:
        if(timer < 25)
        begin
          timer <= timer +1;
          state <= BLINK;
        end
        else
        begin
          timer <= 0;
          state <= FINISH;
        end

      default state <= IDLE;
    endcase

  end

  // for SSDs
  always @ (*)
  begin

    case(state)
      IDLE:
      begin
        SSD0 = NONE;
        SSD1 = NONE;
        SSD2 = NONE;
        SSD3 = NONE;
        SSD4 = NONE;
        SSD5 = NONE;
        SSD6 = NONE;
        SSD7 = NONE;
      end
      DSP:
      begin
        if(scoreB == 0)
          SSD0 = ZERO;
        else if(scoreB == 1)
          SSD0 = ONE;
        else if(scoreB == 2)
          SSD0 = TWO;
        else if(scoreB == 3)
          SSD0 = THREE;
        else
          SSD0 = NONE;

        SSD1 = 7'b1111110;

        if(scoreA == 0)
          SSD2 = ZERO;
        else if(scoreA == 1)
          SSD2 = ONE;
        else if(scoreA == 2)
          SSD2 = TWO;
        else if(scoreA == 3)
          SSD2 = THREE;
        else
          SSD2 = NONE;

        SSD3 = NONE;

        if(YCOORD == 0)
          SSD4 = ZERO;
        else if(YCOORD == 1)
          SSD4 = ONE;
        else if(YCOORD == 2)
          SSD4 = TWO;
        else if(YCOORD == 3)
          SSD4 = THREE;
        else if(YCOORD == 4)
          SSD4 = FOUR;
        else
          SSD4 = NONE;

        SSD5 = NONE;

        SSD6 = NONE;
        SSD7 = NONE;
      end
      HITA:
      begin
        SSD0 = NONE;
        SSD1 = NONE;
        SSD2 = NONE;
        SSD3 = NONE;

        if(YCOORD == 0)
          SSD4 = ZERO;
        else if(YCOORD == 1)
          SSD4 = ONE;
        else if(YCOORD == 2)
          SSD4 = TWO;
        else if(YCOORD == 3)
          SSD4 = THREE;
        else if(YCOORD == 4)
          SSD4 = FOUR;
        else
          SSD4 = NONE;


        SSD5 = NONE;

        SSD6 = NONE;
        SSD7 = NONE;
      end
      HITB:
      begin
        SSD0 = NONE;
        SSD1 = NONE;
        SSD2 = NONE;
        SSD3 = NONE;

        if(YCOORD == 0)
          SSD4 = ZERO;
        else if(YCOORD == 1)
          SSD4 = ONE;
        else if(YCOORD == 2)
          SSD4 = TWO;
        else if(YCOORD == 3)
          SSD4 = THREE;
        else if(YCOORD == 4)
          SSD4 = FOUR;
        else
          SSD4 = NONE;


        SSD5 = NONE;

        SSD6 = NONE;
        SSD7 = NONE;
      end
      SENDA:
      begin
        SSD0 = NONE;
        SSD1 = NONE;
        SSD2 = NONE;
        SSD3 = NONE;

        if(YCOORD == 0)
          SSD4 = ZERO;
        else if(YCOORD == 1)
          SSD4 = ONE;
        else if(YCOORD == 2)
          SSD4 = TWO;
        else if(YCOORD == 3)
          SSD4 = THREE;
        else if(YCOORD == 4)
          SSD4 = FOUR;
        else
          SSD4 = NONE;


        SSD5 = NONE;

        SSD6 = NONE;
        SSD7 = NONE;
      end
      SENDB:
      begin
        SSD0 = NONE;
        SSD1 = NONE;
        SSD2 = NONE;
        SSD3 = NONE;

        if(YCOORD == 0)
          SSD4 = ZERO;
        else if(YCOORD == 1)
          SSD4 = ONE;
        else if(YCOORD == 2)
          SSD4 = TWO;
        else if(YCOORD == 3)
          SSD4 = THREE;
        else if(YCOORD == 4)
          SSD4 = FOUR;
        else
          SSD4 = NONE;

        SSD5 = NONE;

        SSD6 = NONE;
        SSD7 = NONE;
      end
      RESPA:
      begin
        SSD0 = NONE;
        SSD1 = NONE;
        SSD2 = NONE;
        SSD3 = NONE;

        if(YCOORD == 0)
          SSD4 = ZERO;
        else if(YCOORD == 1)
          SSD4 = ONE;
        else if(YCOORD == 2)
          SSD4 = TWO;
        else if(YCOORD == 3)
          SSD4 = THREE;
        else if(YCOORD == 4)
          SSD4 = FOUR;
        else
          SSD4 = NONE;


        SSD5 = NONE;

        SSD6 = NONE;
        SSD7 = NONE;
      end
      RESPB:
      begin
        SSD0 = NONE;
        SSD1 = NONE;
        SSD2 = NONE;
        SSD3 = NONE;

        if(YCOORD == 0)
          SSD4 = ZERO;
        else if(YCOORD == 1)
          SSD4 = ONE;
        else if(YCOORD == 2)
          SSD4 = TWO;
        else if(YCOORD == 3)
          SSD4 = THREE;
        else if(YCOORD == 4)
          SSD4 = FOUR;
        else
          SSD4 = NONE;

        SSD5 = NONE;

        SSD6 = NONE;
        SSD7 = NONE;
      end
      GOALA:
      begin
        if(scoreB == 0)
          SSD0 = ZERO;
        else if(scoreB == 1)
          SSD0 = ONE;
        else if(scoreB == 2)
          SSD0 = TWO;
        else if(scoreB == 3)
          SSD0 = THREE;
        else
          SSD0 = NONE;

        SSD1 = 7'b1111110;

        if(scoreA == 0)
          SSD2 = ZERO;
        else if(scoreA == 1)
          SSD2 = ONE;
        else if(scoreA == 2)
          SSD2 = TWO;
        else if(scoreA == 3)
          SSD2 = THREE;
        else
          SSD2 = NONE;

        SSD3 = NONE;

        if(YCOORD == 0)
          SSD4 = ZERO;
        else if(YCOORD == 1)
          SSD4 = ONE;
        else if(YCOORD == 2)
          SSD4 = TWO;
        else if(YCOORD == 3)
          SSD4 = THREE;
        else if(YCOORD == 4)
          SSD4 = FOUR;
        else
          SSD4 = NONE;
        SSD5 = NONE;

        SSD6 = NONE;
        SSD7 = NONE;
      end
      GOALB:
      begin
        if(scoreB == 0)
          SSD0 = ZERO;
        else if(scoreB == 1)
          SSD0 = ONE;
        else if(scoreB == 2)
          SSD0 = TWO;
        else if(scoreB == 3)
          SSD0 = THREE;
        else
          SSD0 = NONE;

        SSD1 = 7'b1111110;

        if(scoreA == 0)
          SSD2 = ZERO;
        else if(scoreA == 1)
          SSD2 = ONE;
        else if(scoreA == 2)
          SSD2 = TWO;
        else if(scoreA == 3)
          SSD2 = THREE;
        else
          SSD2 = NONE;

        SSD3 = NONE;

        if(YCOORD == 0)
          SSD4 = ZERO;
        else if(YCOORD == 1)
          SSD4 = ONE;
        else if(YCOORD == 2)
          SSD4 = TWO;
        else if(YCOORD == 3)
          SSD4 = THREE;
        else if(YCOORD == 4)
          SSD4 = FOUR;
        else
          SSD4 = NONE;

        SSD5 = NONE;

        SSD6 = NONE;
        SSD7 = NONE;
      end
      FINISH:
      begin
        if(scoreB == 0)
          SSD0 = ZERO;
        else if(scoreB == 1)
          SSD0 = ONE;
        else if(scoreB == 2)
          SSD0 = TWO;
        else if(scoreB == 3)
          SSD0 = THREE;
        else
          SSD0 = NONE;

        SSD1 = 7'b1111110;

        if(scoreA == 0)
          SSD2 = ZERO;
        else if(scoreA == 1)
          SSD2 = ONE;
        else if(scoreA == 2)
          SSD2 = TWO;
        else if(scoreA == 3)
          SSD2 = THREE;
        else
          SSD2 = NONE;

        SSD3 = NONE;

        if(YCOORD == 0)
          SSD4 = ZERO;
        else if(YCOORD == 1)
          SSD4 = ONE;
        else if(YCOORD == 2)
          SSD4 = TWO;
        else if(YCOORD == 3)
          SSD4 = THREE;
        else if(YCOORD == 4)
          SSD4 = FOUR;
        else
          SSD4 = NONE;

        SSD5 = NONE;

        SSD6 = NONE;
        SSD7 = NONE;
      end

      BLINK:

      begin
        if(scoreB == 0)
          SSD0 = ZERO;
        else if(scoreB == 1)
          SSD0 = ONE;
        else if(scoreB == 2)
          SSD0 = TWO;
        else if(scoreB == 3)
          SSD0 = THREE;
        else
          SSD0 = NONE;

        SSD1 = 7'b1111110;

        if(scoreA == 0)
          SSD2 = ZERO;
        else if(scoreA == 1)
          SSD2 = ONE;
        else if(scoreA == 2)
          SSD2 = TWO;
        else if(scoreA == 3)
          SSD2 = THREE;
        else
          SSD2 = NONE;

        SSD3 = NONE;

        if(YCOORD == 0)
          SSD4 = ZERO;
        else if(YCOORD == 1)
          SSD4 = ONE;
        else if(YCOORD == 2)
          SSD4 = TWO;
        else if(YCOORD == 3)
          SSD4 = THREE;
        else if(YCOORD == 4)
          SSD4 = FOUR;
        else
          SSD4 = NONE;

        SSD5 = NONE;

        SSD6 = NONE;
        SSD7 = NONE;
      end

      default:
      begin
        SSD0 = NONE;
        SSD1 = NONE;
        SSD2 = NONE;
        SSD3 = NONE;
        SSD4 = NONE;
        SSD5 = NONE;
        SSD6 = NONE;
        SSD7 = NONE;
      end

    endcase
  end


  //for LEDs
  always @ (*)
  begin
    case(state)
      IDLE:
      begin
        LEDA = 0;
        LEDB = 0;
        LEDX = 0;
      end
      DSP:
      begin
        LEDA = 0;
        LEDB = 0;
        LEDX = 0;
      end
      HITA:
      begin
        LEDA = 1;
        LEDB = 0;
        LEDX = 0;
      end
      HITB:
      begin
        LEDA = 0;
        LEDB = 1;
        LEDX = 0;
      end
      SENDA:
      begin
        LEDA = 0;
        LEDB = 0;
        if(XCOORD == 0)
          LEDX = 1;
        else if(XCOORD == 1)
          LEDX = 2;
        else if(XCOORD == 2)
          LEDX = 4;
        else if(XCOORD == 3)
          LEDX = 8;
        else if(XCOORD == 4)
          LEDX = 16;
      end
      SENDB:
      begin
        LEDA = 0;
        LEDB = 0;
        if(XCOORD == 0)
          LEDX = 1;
        else if(XCOORD == 1)
          LEDX = 2;
        else if(XCOORD == 2)
          LEDX = 4;
        else if(XCOORD == 3)
          LEDX = 8;
        else if(XCOORD == 4)
          LEDX = 16;
      end
      RESPA:
      begin
        LEDA = 0;
        LEDB = 0;
        if(XCOORD == 0)
          LEDX = 1;
        else if(XCOORD == 1)
          LEDX = 2;
        else if(XCOORD == 2)
          LEDX = 4;
        else if(XCOORD == 3)
          LEDX = 8;
        else if(XCOORD == 4)
          LEDX = 16;
      end
      RESPB:
      begin
        LEDA = 0;
        LEDB = 0;
        if(XCOORD == 0)
          LEDX = 1;
        else if(XCOORD == 1)
          LEDX = 2;
        else if(XCOORD == 2)
          LEDX = 4;
        else if(XCOORD == 3)
          LEDX = 8;
        else if(XCOORD == 4)
          LEDX = 16;
      end
      GOALA:
      begin
        LEDA = 0;
        LEDB = 0;
        LEDX = 5'b10001;
      end
      GOALB:
      begin
        LEDA = 0;
        LEDB = 0;
        LEDX = 5'b10001;
      end
      FINISH:
      begin
        LEDA = 0;
        LEDB = 0;
        LEDX = 5'b10001;
      end

      BLINK:
      begin
        LEDA = 0;
        LEDB = 0;
        LEDX = 0;
      end

      default:
      begin
        LEDA = 0;
        LEDB = 0;
        LEDX = 0;
      end
    endcase
  end


endmodule

hockey_tb.v
module hockey_tb();


  parameter HP = 5;       // Half period of our clock signal
  parameter FP = (2*HP);  // Full period of our clock signal

  reg clk, rst, BTNA, BTNB;
  reg [1:0] DIRA;
  reg [1:0] DIRB;
  reg [2:0] YA;
  reg [2:0] YB;
  
  wire [6:0] SSD0,SSD1,SSD2,SSD3,SSD4,SSD5,SSD6,SSD7;

  wire LEDA;
  wire LEDB;
  wire [4:0] LEDX;

  wire [2:0] Y;
  wire [2:0] X;

  // Our design-under-test is the DigiHockey module
  hockey dut(clk, rst, BTNA, BTNB, DIRA, DIRB, YA, YB,LEDA,LEDB,LEDX, SSD7,SSD6,SSD5,SSD4,SSD3,SSD2,SSD1,SSD0, Y,X);

  // This always statement automatically cycles between clock high and clock low in HP (Half Period) time. Makes writing test-benches easier.
  always #HP clk = ~clk;

  initial
  begin
	$dumpfile("DigiHockey.vcd"); //  * Our waveform is saved under this file.
    $dumpvars(0,hockey_tb); // * Get the variables from the module.
	$display("Simulation started.");

  clk = 0;
  #HP
  rst = 1;
  #FP
  rst = 0;
  YA = 0;
  BTNA = 1;
  BTNB = 0;
  #FP
  #FP
  BTNA = 0; 
  #30
  BTNA = 1;
  #30
  BTNA =0;
  #5000

  
  // Here, you are asked to write your test scenario.



	$display("Simulation finished.");
    $finish(); // Finish simulation.
  end



endmodule

DigiHockey.vcd
$date
	Thu Jan 04 11:14:18 2024
$end
$version
	Icarus Verilog
$end
$timescale
	1s
$end
$scope module hockey_tb $end
$var wire 3 ! Y [2:0] $end
$var wire 3 " X [2:0] $end
$var wire 7 # SSD7 [6:0] $end
$var wire 7 $ SSD6 [6:0] $end
$var wire 7 % SSD5 [6:0] $end
$var wire 7 & SSD4 [6:0] $end
$var wire 7 ' SSD3 [6:0] $end
$var wire 7 ( SSD2 [6:0] $end
$var wire 7 ) SSD1 [6:0] $end
$var wire 7 * SSD0 [6:0] $end
$var wire 5 + LEDX [4:0] $end
$var wire 1 , LEDB $end
$var wire 1 - LEDA $end
$var parameter 64 . FP $end
$var parameter 32 / HP $end
$var reg 1 0 BTNA $end
$var reg 1 1 BTNB $end
$var reg 2 2 DIRA [1:0] $end
$var reg 2 3 DIRB [1:0] $end
$var reg 3 4 YA [2:0] $end
$var reg 3 5 YB [2:0] $end
$var reg 1 6 clk $end
$var reg 1 7 rst $end
$scope module dut $end
$var wire 1 0 BTNA $end
$var wire 1 1 BTNB $end
$var wire 2 8 DIRA [1:0] $end
$var wire 2 9 DIRB [1:0] $end
$var wire 3 : YA [2:0] $end
$var wire 3 ; YB [2:0] $end
$var wire 1 6 clk $end
$var wire 1 7 rst $end
$var parameter 4 < BLINK $end
$var parameter 4 = DSP $end
$var parameter 4 > FINISH $end
$var parameter 7 ? FOUR $end
$var parameter 4 @ GOALA $end
$var parameter 4 A GOALB $end
$var parameter 4 B HITA $end
$var parameter 4 C HITB $end
$var parameter 4 D IDLE $end
$var parameter 7 E NONE $end
$var parameter 7 F ONE $end
$var parameter 4 G RESPA $end
$var parameter 4 H RESPB $end
$var parameter 4 I SENDA $end
$var parameter 4 J SENDB $end
$var parameter 7 K THREE $end
$var parameter 7 L TWO $end
$var parameter 7 M ZERO $end
$var reg 1 - LEDA $end
$var reg 1 , LEDB $end
$var reg 5 N LEDX [4:0] $end
$var reg 7 O SSD0 [6:0] $end
$var reg 7 P SSD1 [6:0] $end
$var reg 7 Q SSD2 [6:0] $end
$var reg 7 R SSD3 [6:0] $end
$var reg 7 S SSD4 [6:0] $end
$var reg 7 T SSD5 [6:0] $end
$var reg 7 U SSD6 [6:0] $end
$var reg 7 V SSD7 [6:0] $end
$var reg 3 W XCOORD [2:0] $end
$var reg 3 X YCOORD [2:0] $end
$var reg 2 Y buttons [1:0] $end
$var reg 2 Z dirY [1:0] $end
$var reg 2 [ scoreA [1:0] $end
$var reg 2 \ scoreB [1:0] $end
$var reg 4 ] state [3:0] $end
$var reg 9 ^ timer [8:0] $end
$var reg 1 _ turn $end
$upscope $end
$upscope $end
$enddefinitions $end
$comment Show the parameter values. $end
$dumpall
b1 M
b10010 L
b110 K
b100 J
b101 I
b111 H
b110 G
b1001111 F
b1111111 E
b0 D
b10 C
b11 B
b1001 A
b1000 @
b1001100 ?
b1010 >
b1 =
b1011 <
b101 /
b1010 .
$end
#0
$dumpvars
x_
bx ^
bx ]
bx \
bx [
bx Z
bx Y
bx X
bx W
bx V
bx U
bx T
bx S
bx R
bx Q
bx P
bx O
bx N
bx ;
bx :
bx 9
bx 8
x7
06
bx 5
bx 4
bx 3
bx 2
x1
x0
x-
x,
bx +
bx *
bx )
bx (
bx '
bx &
bx %
bx $
bx #
bx "
bx !
$end
#5
b0 \
b0 [
b0 ^
b0 ]
b1111111 #
b1111111 V
b1111111 $
b1111111 U
b1111111 %
b1111111 T
b1111111 &
b1111111 S
b1111111 '
b1111111 R
b1111111 (
b1111111 Q
b1111111 )
b1111111 P
b1111111 *
b1111111 O
b0 +
b0 N
0,
0-
b0 "
b0 X
b0 !
b0 W
17
16
#10
06
#15
b1 &
b1 S
b1 (
b1 Q
b1111110 )
b1111110 P
b1 *
b1 O
b1 ]
0_
b10 Y
16
01
10
b0 4
b0 :
07
#20
06
#25
b1 ^
16
#30
06
#35
b10 ^
16
00
#40
06
#45
b11 ^
16
#50
06
#55
b100 ^
16
#60
06
#65
b101 ^
16
10
#70
06
#75
b110 ^
16
#80
06
#85
b111 ^
16
#90
06
#95
b1000 ^
16
00
#100
06
#105
b1001 ^
16
#110
06
#115
b1010 ^
16
#120
06
#125
b1011 ^
16
#130
06
#135
b1100 ^
16
#140
06
#145
b1101 ^
16
#150
06
#155
b1110 ^
16
#160
06
#165
b1111 ^
16
#170
06
#175
b10000 ^
16
#180
06
#185
b10001 ^
16
#190
06
#195
b10010 ^
16
#200
06
#205
b10011 ^
16
#210
06
#215
b10100 ^
16
#220
06
#225
b10101 ^
16
#230
06
#235
b10110 ^
16
#240
06
#245
b10111 ^
16
#250
06
#255
b11000 ^
16
#260
06
#265
b11001 ^
16
#270
06
#275
b11010 ^
16
#280
06
#285
b11011 ^
16
#290
06
#295
b11100 ^
16
#300
06
#305
b11101 ^
16
#310
06
#315
b11110 ^
16
#320
06
#325
b11111 ^
16
#330
06
#335
b100000 ^
16
#340
06
#345
b100001 ^
16
#350
06
#355
b100010 ^
16
#360
06
#365
b100011 ^
16
#370
06
#375
b100100 ^
16
#380
06
#385
b100101 ^
16
#390
06
#395
b100110 ^
16
#400
06
#405
b100111 ^
16
#410
06
#415
b101000 ^
16
#420
06
#425
b101001 ^
16
#430
06
#435
b101010 ^
16
#440
06
#445
b101011 ^
16
#450
06
#455
b101100 ^
16
#460
06
#465
b101101 ^
16
#470
06
#475
b101110 ^
16
#480
06
#485
b101111 ^
16
#490
06
#495
b110000 ^
16
#500
06
#505
b110001 ^
16
#510
06
#515
b110010 ^
16
#520
06
#525
b110011 ^
16
#530
06
#535
b110100 ^
16
#540
06
#545
b110101 ^
16
#550
06
#555
b110110 ^
16
#560
06
#565
b110111 ^
16
#570
06
#575
b111000 ^
16
#580
06
#585
b111001 ^
16
#590
06
#595
b111010 ^
16
#600
06
#605
b111011 ^
16
#610
06
#615
b111100 ^
16
#620
06
#625
b111101 ^
16
#630
06
#635
b111110 ^
16
#640
06
#645
b111111 ^
16
#650
06
#655
b1000000 ^
16
#660
06
#665
b1000001 ^
16
#670
06
#675
b1000010 ^
16
#680
06
#685
b1000011 ^
16
#690
06
#695
b1000100 ^
16
#700
06
#705
b1000101 ^
16
#710
06
#715
b1000110 ^
16
#720
06
#725
b1000111 ^
16
#730
06
#735
b1001000 ^
16
#740
06
#745
b1001001 ^
16
#750
06
#755
b1001010 ^
16
#760
06
#765
b1001011 ^
16
#770
06
#775
b1001100 ^
16
#780
06
#785
b1001101 ^
16
#790
06
#795
b1001110 ^
16
#800
06
#805
b1001111 ^
16
#810
06
#815
b1010000 ^
16
#820
06
#825
b1010001 ^
16
#830
06
#835
b1010010 ^
16
#840
06
#845
b1010011 ^
16
#850
06
#855
b1010100 ^
16
#860
06
#865
b1010101 ^
16
#870
06
#875
b1010110 ^
16
#880
06
#885
b1010111 ^
16
#890
06
#895
b1011000 ^
16
#900
06
#905
b1011001 ^
16
#910
06
#915
b1011010 ^
16
#920
06
#925
b1011011 ^
16
#930
06
#935
b1011100 ^
16
#940
06
#945
b1011101 ^
16
#950
06
#955
b1011110 ^
16
#960
06
#965
b1011111 ^
16
#970
06
#975
b1100000 ^
16
#980
06
#985
b1100001 ^
16
#990
06
#995
b1100010 ^
16
#1000
06
#1005
b1100011 ^
16
#1010
06
#1015
b1100100 ^
16
#1020
06
#1025
1-
b1111111 (
b1111111 Q
b1111111 )
b1111111 P
b1111111 *
b1111111 O
b0 ^
b11 ]
16
